ovos_stt_plugin_onnx_asr-0.0.1.dist-info/licenses/LICENSE
ovos_stt_plugin_onnxasr/__init__.py
ovos_stt_plugin_onnxasr/version.py
ovos_stt_plugin_onnx_asr-0.0.1.dist-info/METADATA
ovos_stt_plugin_onnx_asr-0.0.1.dist-info/WHEEL
ovos_stt_plugin_onnx_asr-0.0.1.dist-info/entry_points.txt
ovos_stt_plugin_onnx_asr-0.0.1.dist-info/top_level.txt
ovos_stt_plugin_onnx_asr-0.0.1.dist-info/zip-safe
ovos_stt_plugin_onnx_asr-0.0.1.dist-info/RECORD
