Metadata-Version: 2.4
Name: ovos-stt-plugin-onnx-asr
Version: 0.0.1
Summary: A onnx stt plugin for OVOS
Home-page: https://github.com/OpenVoiceOS/ovos-stt-plugin-onnx-asr
Author: JarbasAi
Author-email: jarbasai@mailfence.com
License: Apache-2.0
Keywords: ovos plugin stt
Classifier: Development Status :: 3 - Alpha
Classifier: Intended Audience :: Developers
Classifier: License :: OSI Approved :: Apache Software License
License-File: LICENSE
Requires-Dist: ovos-plugin-manager<3.0.0,>=2.1.1
Requires-Dist: onnx_asr
Dynamic: author
Dynamic: author-email
Dynamic: classifier
Dynamic: home-page
Dynamic: keywords
Dynamic: license
Dynamic: license-file
Dynamic: requires-dist
Dynamic: summary
